{
	"pattrstorage" : 	{
		"name" : "twinkler-storage",
		"slots" : 		{
			"1" : 			{
				"id" : 1,
				"data" : 				{
					"bpm" : [ 120 ],
					"live.text" : [  ],
					"maxdel" : [ 120 ],
					"pitch-classes" : [ 0, 2, 4, 6, 7, 9, 10 ],
					"rezon-gain" : [ -5.968504 ],
					"transp" : [ 0 ],
					"rezon8r::autopan" : [ 1.0 ],
					"rezon8r::feedback" : [ 0.949606 ],
					"rezon8r::detune" : [ 0.0 ],
					"rezon8r::width" : [ 1.0 ],
					"rezon8r::wetdry" : [ 1.0 ],
					"rezon8r::negative" : [ 1 ],
					"rezon8r::cutoff" : [ 20000.0 ],
					"1delayr::deltime" : [ 250.0 ],
					"1delayr::feedback" : [ 0.5 ],
					"1delayr::wetdry" : [ 0.295276 ],
					"wavr::bend" : [ 0.0 ],
					"wavr::dutycycle" : [ 0.141732 ],
					"wavr::portamento" : [ 50.0 ],
					"wavr::polyphony" : [ 12.0 ],
					"wavr::pan" : [ 0.0 ],
					"wavr::release" : [ 93.700787 ],
					"wavr::vibdepth" : [ 0.264567 ],
					"wavr::vibrate" : [ 6.0 ],
					"wavr::vibwave" : [ 0.0 ],
					"wavr::sustain" : [ 0.50315 ],
					"wavr::decay" : [ 20.0 ],
					"wavr::attack" : [ 20.0 ],
					"wavr::oscwave" : [ 1.0 ],
					"reverber8r::roomsize" : [ 0.26063 ],
					"reverber8r::decaytime" : [ 0.41811 ],
					"reverber8r::wetdry" : [ 1.0 ],
					"reverber8r::cutoff" : [ 1.0 ]
				}

			}
,
			"2" : 			{
				"id" : 2,
				"data" : 				{
					"bpm" : [ 120 ],
					"live.text" : [ 0.0 ],
					"maxdel" : [ 120 ],
					"pitch-classes" : [ 7, 4, 3, 0, 0, 0, 0 ],
					"rezon-gain" : [ -5.968504 ],
					"transp" : [ 0 ],
					"rezon8r::autopan" : [ 1.0 ],
					"rezon8r::feedback" : [ 0.744882 ],
					"rezon8r::detune" : [ 0.0 ],
					"rezon8r::width" : [ 1.0 ],
					"rezon8r::wetdry" : [ 1.0 ],
					"rezon8r::negative" : [ 0 ],
					"rezon8r::cutoff" : [ 20000.0 ],
					"1delayr::deltime" : [ 124.141732 ],
					"1delayr::feedback" : [ 0.350394 ],
					"1delayr::wetdry" : [ 0.728347 ],
					"wavr::bend" : [ 0.0 ],
					"wavr::dutycycle" : [ 0.220472 ],
					"wavr::portamento" : [ 45.275591 ],
					"wavr::polyphony" : [ 1.0 ],
					"wavr::pan" : [ 0.0 ],
					"wavr::release" : [ 70.07874 ],
					"wavr::vibdepth" : [ 0.680315 ],
					"wavr::vibrate" : [ 6.0 ],
					"wavr::vibwave" : [ 2.0 ],
					"wavr::sustain" : [ 0.26693 ],
					"wavr::decay" : [ 20.0 ],
					"wavr::attack" : [ 20.0 ],
					"wavr::oscwave" : [ 2.0 ],
					"reverber8r::roomsize" : [ 0.26063 ],
					"reverber8r::decaytime" : [ 0.41811 ],
					"reverber8r::wetdry" : [ 0.779528 ],
					"reverber8r::cutoff" : [ 1.0 ]
				}

			}
,
			"3" : 			{
				"id" : 3,
				"data" : 				{
					"bpm" : [ 30 ],
					"live.text" : [  ],
					"maxdel" : [ 400 ],
					"pitch-classes" : [ 0, 2, 4, 6, 7, 9, 10 ],
					"rezon-gain" : [ -8.981558 ],
					"transp" : [ 0 ],
					"rezon8r::autopan" : [ 1.0 ],
					"rezon8r::feedback" : [ 0.949606 ],
					"rezon8r::detune" : [ 0.0 ],
					"rezon8r::width" : [ 1.0 ],
					"rezon8r::wetdry" : [ 1.0 ],
					"rezon8r::negative" : [ 1 ],
					"rezon8r::cutoff" : [ 2000.0 ],
					"1delayr::deltime" : [ 918.622047 ],
					"1delayr::feedback" : [ 0.704724 ],
					"1delayr::wetdry" : [ 0.30315 ],
					"wavr::bend" : [ 0.0 ],
					"wavr::dutycycle" : [ 0.0 ],
					"wavr::portamento" : [ 50.0 ],
					"wavr::polyphony" : [ 12.0 ],
					"wavr::pan" : [ 0.0 ],
					"wavr::release" : [ 1000.0 ],
					"wavr::vibdepth" : [ 0.132283 ],
					"wavr::vibrate" : [ 5.0 ],
					"wavr::vibwave" : [ 0.0 ],
					"wavr::sustain" : [ 1.0 ],
					"wavr::decay" : [ 185.354331 ],
					"wavr::attack" : [ 500.0 ],
					"wavr::oscwave" : [ 1.0 ],
					"reverber8r::roomsize" : [ 0.26063 ],
					"reverber8r::decaytime" : [ 0.41811 ],
					"reverber8r::wetdry" : [ 1.0 ],
					"reverber8r::cutoff" : [ 1.0 ]
				}

			}
,
			"4" : 			{
				"id" : 4,
				"data" : 				{
					"bpm" : [ 60 ],
					"live.text" : [  ],
					"maxdel" : [ 260 ],
					"pitch-classes" : [ 0, 0, 1, 5, 6, 9, 10 ],
					"rezon-gain" : [ -11.651057 ],
					"transp" : [ 0 ],
					"rezon8r::autopan" : [ 1.0 ],
					"rezon8r::feedback" : [ 0.968504 ],
					"rezon8r::detune" : [ 0.0 ],
					"rezon8r::width" : [ 0.559055 ],
					"rezon8r::wetdry" : [ 1.0 ],
					"rezon8r::negative" : [ 0 ],
					"rezon8r::cutoff" : [ 18000.0 ],
					"1delayr::deltime" : [ 423.055118 ],
					"1delayr::feedback" : [ 0.602362 ],
					"1delayr::wetdry" : [ 0.30315 ],
					"wavr::bend" : [ -0.661417 ],
					"wavr::dutycycle" : [ 0.110236 ],
					"wavr::portamento" : [ 19.685039 ],
					"wavr::polyphony" : [ 1.0 ],
					"wavr::pan" : [ 0.0 ],
					"wavr::release" : [ 188.976378 ],
					"wavr::vibdepth" : [ 2.711811 ],
					"wavr::vibrate" : [ 20.0 ],
					"wavr::vibwave" : [ 3.0 ],
					"wavr::sustain" : [ 0.437008 ],
					"wavr::decay" : [ 67.244094 ],
					"wavr::attack" : [ 362.204724 ],
					"wavr::oscwave" : [ 2.0 ],
					"reverber8r::roomsize" : [ 0.922047 ],
					"reverber8r::decaytime" : [ 0.882677 ],
					"reverber8r::wetdry" : [ 0.503937 ],
					"reverber8r::cutoff" : [ 1.0 ]
				}

			}
,
			"5" : 			{
				"id" : 5,
				"data" : 				{
					"bpm" : [ 120 ],
					"live.text" : [  ],
					"maxdel" : [ 20 ],
					"pitch-classes" : [ 0, 0, 6, 0, 0, 10, 0 ],
					"rezon-gain" : [ -5.968504 ],
					"transp" : [ -24 ],
					"rezon8r::autopan" : [ 1.0 ],
					"rezon8r::feedback" : [ 0.949606 ],
					"rezon8r::detune" : [ 0.0 ],
					"rezon8r::width" : [ 1.0 ],
					"rezon8r::wetdry" : [ 1.0 ],
					"rezon8r::negative" : [ 1 ],
					"rezon8r::cutoff" : [ 20000.0 ],
					"1delayr::deltime" : [ 250.0 ],
					"1delayr::feedback" : [ 0.5 ],
					"1delayr::wetdry" : [ 0.295276 ],
					"wavr::bend" : [ 0.0 ],
					"wavr::dutycycle" : [ 0.937008 ],
					"wavr::portamento" : [ 50.0 ],
					"wavr::polyphony" : [ 12.0 ],
					"wavr::pan" : [ 0.0 ],
					"wavr::release" : [ 220.472441 ],
					"wavr::vibdepth" : [ 0.393577 ],
					"wavr::vibrate" : [ 17.806299 ],
					"wavr::vibwave" : [ 3.0 ],
					"wavr::sustain" : [ 0.099213 ],
					"wavr::decay" : [ 15.748031 ],
					"wavr::attack" : [ 0.0 ],
					"wavr::oscwave" : [ 2.0 ],
					"reverber8r::roomsize" : [ 0.26063 ],
					"reverber8r::decaytime" : [ 0.41811 ],
					"reverber8r::wetdry" : [ 1.0 ],
					"reverber8r::cutoff" : [ 1.0 ]
				}

			}

		}

	}

}
